{
  "id": 16119,
  "islong": 2,
  "direction": 1,
  "title": "相反相成",
  "is_dmzj": 0,
  "cover": "https://images.dmzj.com/webpic/16/xiangfanxiangcheng.jpg",
  "description": "怎么都看他不顺眼，我和他是竞争对手？是伙伴，还是……？",
  "last_updatetime": 1416058951,
  "last_update_chapter_name": "全一话",
  "copyright": 0,
  "first_letter": "x",
  "comic_py": "xiangfanxiangcheng",
  "hidden": 0,
  "hot_num": 55918,
  "hit_num": 164701,
  "uid": null,
  "is_lock": 0,
  "last_update_chapter_id": 32242,
  "status": [
    {
      "tag_id": 2310,
      "tag_name": "已完结"
    }
  ],
  "types": [
    {
      "tag_id": 3246,
      "tag_name": "纯爱"
    }
  ],
  "authors": [
    {
      "tag_id": 8022,
      "tag_name": "鸢田濑ケビン"
    }
  ],
  "subscribe_num": 356,
  "chapters": [
    {
      "title": "连载",
      "data": [
        {
          "chapter_id": 32242,
          "chapter_title": "1话",
          "updatetime": 1416058951,
          "filesize": 3217881,
          "chapter_order": 10
        }
      ]
    }
  ],
  "comment": {
    "comment_count": 10,
    "latest_comment": [
      {
        "comment_id": 15476689,
        "uid": 106218532,
        "content": "太美妙了吧",
        "createtime": 1557159445,
        "nickname": "hans！",
        "avatar": "https://avatar.dmzj.com/71/94/7194306e0a433f877fada8fbb293371e.png"
      },
      {
        "comment_id": 12210341,
        "uid": 106010436,
        "content": "老师的早期作品呀。",
        "createtime": 1551531469,
        "nickname": "咩塔利卡",
        "avatar": "https://avatar.dmzj.com/74/34/7434fd9c0378bb10a5021a9701a80e64.png"
      }
    ]
  },
  "is_need_login": 0
}