{
  "id": 2646,
  "islong": 2,
  "direction": 1,
  "title": "海虎Ⅱ",
  "is_dmzj": 0,
  "cover": "https://images.dmzj.com/webpic/6/001_c34cec4faea027ca134f544e9936131f.jpg",
  "description": "海虎與地獄緩緩的向天空島進發. 海虎和地獄當年實際上只用了五百年已能完全回復記憶. 只是把\"找人\"的工夫交給武男. 除了海虎曾數次出來. 找尋地獄, 奧加, 白武男和小瞳 ...",
  "last_updatetime": 1435207485,
  "copyright": 0,
  "first_letter": "h",
  "hot_num": 271526,
  "hit_num": 2121269,
  "uid": null,
  "types": [
    {
      "tag_id": 6,
      "tag_name": "格斗"
    }
  ],
  "authors": [
    {
      "tag_id": 1208,
      "tag_name": "邓志辉"
    }
  ],
  "status": [
    {
      "tag_id": 2310,
      "tag_name": "已完结"
    }
  ],
  "subscribe_num": 1172,
  "chapters": [
    {
      "title": "连载",
      "data": [
        {
          "chapter_id": 40142,
          "chapter_title": "51卷",
          "updatetime": 1435207485,
          "filesize": 4944935,
          "chapter_order": 510
        },
        {
          "chapter_id": 40141,
          "chapter_title": "50卷",
          "updatetime": 1435207037,
          "filesize": 4632354,
          "chapter_order": 500
        },
        {
          "chapter_id": 39682,
          "chapter_title": "49卷",
          "updatetime": 1433837657,
          "filesize": 4261909,
          "chapter_order": 490
        },
        {
          "chapter_id": 5624,
          "chapter_title": "48卷",
          "updatetime": 1272438728,
          "filesize": 2865933,
          "chapter_order": 480
        },
        {
          "chapter_id": 5623,
          "chapter_title": "47卷",
          "updatetime": 1272438728,
          "filesize": 2609214,
          "chapter_order": 470
        },
        {
          "chapter_id": 5622,
          "chapter_title": "46卷",
          "updatetime": 1272438728,
          "filesize": 2720963,
          "chapter_order": 460
        },
        {
          "chapter_id": 5621,
          "chapter_title": "45卷",
          "updatetime": 1272438728,
          "filesize": 2561089,
          "chapter_order": 450
        },
        {
          "chapter_id": 5620,
          "chapter_title": "44卷",
          "updatetime": 1272438728,
          "filesize": 2456898,
          "chapter_order": 440
        },
        {
          "chapter_id": 5619,
          "chapter_title": "43卷",
          "updatetime": 1272438728,
          "filesize": 2654639,
          "chapter_order": 430
        },
        {
          "chapter_id": 5618,
          "chapter_title": "42卷",
          "updatetime": 1272438728,
          "filesize": 2706502,
          "chapter_order": 420
        },
        {
          "chapter_id": 5617,
          "chapter_title": "41卷",
          "updatetime": 1272438728,
          "filesize": 2587206,
          "chapter_order": 410
        },
        {
          "chapter_id": 5616,
          "chapter_title": "40卷",
          "updatetime": 1272438728,
          "filesize": 2897598,
          "chapter_order": 400
        },
        {
          "chapter_id": 5615,
          "chapter_title": "39卷",
          "updatetime": 1272438728,
          "filesize": 2661134,
          "chapter_order": 390
        },
        {
          "chapter_id": 5614,
          "chapter_title": "38卷",
          "updatetime": 1272438728,
          "filesize": 2835721,
          "chapter_order": 380
        },
        {
          "chapter_id": 5613,
          "chapter_title": "37卷",
          "updatetime": 1272438728,
          "filesize": 2422025,
          "chapter_order": 370
        },
        {
          "chapter_id": 5612,
          "chapter_title": "36卷",
          "updatetime": 1272438728,
          "filesize": 3182555,
          "chapter_order": 360
        },
        {
          "chapter_id": 5611,
          "chapter_title": "35卷",
          "updatetime": 1272438728,
          "filesize": 2864743,
          "chapter_order": 350
        },
        {
          "chapter_id": 5610,
          "chapter_title": "34卷",
          "updatetime": 1272438728,
          "filesize": 3219063,
          "chapter_order": 340
        },
        {
          "chapter_id": 5609,
          "chapter_title": "33卷",
          "updatetime": 1272438728,
          "filesize": 2745581,
          "chapter_order": 330
        },
        {
          "chapter_id": 5608,
          "chapter_title": "32卷",
          "updatetime": 1272438728,
          "filesize": 3681394,
          "chapter_order": 320
        },
        {
          "chapter_id": 5607,
          "chapter_title": "31卷",
          "updatetime": 1272438728,
          "filesize": 3868284,
          "chapter_order": 310
        },
        {
          "chapter_id": 5606,
          "chapter_title": "30卷",
          "updatetime": 1272438728,
          "filesize": 3637578,
          "chapter_order": 300
        },
        {
          "chapter_id": 5605,
          "chapter_title": "29卷",
          "updatetime": 1272438728,
          "filesize": 3808739,
          "chapter_order": 290
        },
        {
          "chapter_id": 5604,
          "chapter_title": "28卷",
          "updatetime": 1272438728,
          "filesize": 3453669,
          "chapter_order": 280
        },
        {
          "chapter_id": 5603,
          "chapter_title": "27卷",
          "updatetime": 1272438728,
          "filesize": 3789216,
          "chapter_order": 270
        },
        {
          "chapter_id": 5602,
          "chapter_title": "26卷",
          "updatetime": 1272438728,
          "filesize": 3668291,
          "chapter_order": 260
        },
        {
          "chapter_id": 5601,
          "chapter_title": "25卷",
          "updatetime": 1272438728,
          "filesize": 3970791,
          "chapter_order": 250
        },
        {
          "chapter_id": 5600,
          "chapter_title": "24卷",
          "updatetime": 1272438728,
          "filesize": 3821662,
          "chapter_order": 240
        },
        {
          "chapter_id": 5599,
          "chapter_title": "23卷",
          "updatetime": 1272438728,
          "filesize": 3933156,
          "chapter_order": 230
        },
        {
          "chapter_id": 5598,
          "chapter_title": "22卷",
          "updatetime": 1272438728,
          "filesize": 3980125,
          "chapter_order": 220
        },
        {
          "chapter_id": 5597,
          "chapter_title": "21卷",
          "updatetime": 1272438728,
          "filesize": 3925320,
          "chapter_order": 210
        },
        {
          "chapter_id": 5596,
          "chapter_title": "20卷",
          "updatetime": 1272438728,
          "filesize": 3884134,
          "chapter_order": 200
        },
        {
          "chapter_id": 5595,
          "chapter_title": "19卷",
          "updatetime": 1272438728,
          "filesize": 3695415,
          "chapter_order": 190
        },
        {
          "chapter_id": 5594,
          "chapter_title": "18卷",
          "updatetime": 1272438728,
          "filesize": 4277990,
          "chapter_order": 180
        },
        {
          "chapter_id": 5593,
          "chapter_title": "17卷",
          "updatetime": 1272438728,
          "filesize": 3656857,
          "chapter_order": 170
        },
        {
          "chapter_id": 5592,
          "chapter_title": "16卷",
          "updatetime": 1272438728,
          "filesize": 3874873,
          "chapter_order": 160
        },
        {
          "chapter_id": 5591,
          "chapter_title": "15卷",
          "updatetime": 1272438728,
          "filesize": 3765221,
          "chapter_order": 150
        },
        {
          "chapter_id": 5590,
          "chapter_title": "14卷",
          "updatetime": 1272438728,
          "filesize": 4042207,
          "chapter_order": 140
        },
        {
          "chapter_id": 5589,
          "chapter_title": "13卷",
          "updatetime": 1272438728,
          "filesize": 3823778,
          "chapter_order": 130
        },
        {
          "chapter_id": 5588,
          "chapter_title": "12卷",
          "updatetime": 1272438728,
          "filesize": 3969674,
          "chapter_order": 120
        },
        {
          "chapter_id": 5587,
          "chapter_title": "11卷",
          "updatetime": 1272438728,
          "filesize": 3859516,
          "chapter_order": 110
        },
        {
          "chapter_id": 5586,
          "chapter_title": "10卷",
          "updatetime": 1272438728,
          "filesize": 4044136,
          "chapter_order": 100
        },
        {
          "chapter_id": 5585,
          "chapter_title": "9卷",
          "updatetime": 1272438728,
          "filesize": 3902896,
          "chapter_order": 90
        },
        {
          "chapter_id": 5584,
          "chapter_title": "8卷",
          "updatetime": 1272438728,
          "filesize": 3593463,
          "chapter_order": 80
        },
        {
          "chapter_id": 5583,
          "chapter_title": "7卷",
          "updatetime": 1272438728,
          "filesize": 2605286,
          "chapter_order": 70
        },
        {
          "chapter_id": 5582,
          "chapter_title": "6卷",
          "updatetime": 1272438728,
          "filesize": 2773840,
          "chapter_order": 60
        },
        {
          "chapter_id": 5581,
          "chapter_title": "5卷",
          "updatetime": 1272438728,
          "filesize": 3600380,
          "chapter_order": 50
        },
        {
          "chapter_id": 5580,
          "chapter_title": "4卷",
          "updatetime": 1272438728,
          "filesize": 3552415,
          "chapter_order": 40
        },
        {
          "chapter_id": 5579,
          "chapter_title": "3卷",
          "updatetime": 1272438728,
          "filesize": 2538956,
          "chapter_order": 30
        },
        {
          "chapter_id": 5578,
          "chapter_title": "2卷",
          "updatetime": 1272438728,
          "filesize": 2696349,
          "chapter_order": 20
        },
        {
          "chapter_id": 5577,
          "chapter_title": "1卷",
          "updatetime": 1272438728,
          "filesize": 2683052,
          "chapter_order": 10
        }
      ]
    }
  ],
  "comment": {
    "comment_count": 829,
    "latest_comment": [
      {
        "comment_id": 30072282,
        "uid": 108000205,
        "content": "好耶",
        "createtime": 1598896702,
        "nickname": "dmzj_108000205",
        "avatar": "https://avatar.dmzj.com/8b/c2/8bc2353e9b0297c0835d09e2a6ab4131.png"
      },
      {
        "comment_id": 30045771,
        "uid": 106715362,
        "content": "摩拜热狗学祖师",
        "createtime": 1598792862,
        "nickname": "净化光线",
        "avatar": "https://avatar.dmzj.com/e6/dc/e6dc5648f7ee3fcd6f2dd8373da25cc7.png"
      }
    ]
  }
}