{
  "id": 41779,
  "islong": 2,
  "direction": 2,
  "title": "三界血歌",
  "is_dmzj": 0,
  "cover": "https://images.dmzj.com/img/webpic/10/1003080301507862702.jpg",
  "description": "主角血歌有一个倾国倾城却桀骜叛逆的母亲，一个天地所钟却纨绔不羁的父亲。他一个心底怀着一丝善良和柔软的半妖少年，被逼踏入了席卷三界的漩涡，漫天神、圣、仙、佛都是他的敌人，他只有昂首向前，酣畅高歌，要么踏上三界巅峰，要么永堕幽冥。",
  "last_updatetime": 1507862822,
  "copyright": 1,
  "first_letter": "s",
  "hot_num": 125692,
  "hit_num": 1959183,
  "uid": 100308030,
  "status": [
    {
      "tag_id": 2309,
      "tag_name": "连载中"
    }
  ],
  "types": [
    {
      "tag_id": 3248,
      "tag_name": "热血"
    },
    {
      "tag_id": 5848,
      "tag_name": "奇幻"
    }
  ],
  "authors": [
    {
      "tag_id": 10236,
      "tag_name": "咪咕动漫有限公司"
    }
  ],
  "subscribe_num": 495,
  "chapters": [
    {
      "title": "连载",
      "data": [
        {
          "chapter_id": 65860,
          "chapter_title": "2话",
          "updatetime": 1507862822,
          "filesize": 1255033,
          "chapter_order": 2
        },
        {
          "chapter_id": 65859,
          "chapter_title": "1话",
          "updatetime": 1507862795,
          "filesize": 1330898,
          "chapter_order": 1
        }
      ]
    }
  ],
  "author_notice": "",
  "comic_notice": "【咪咕动漫出品】起点大神血红《三界血歌》小说原著改编。",
  "comment": {
    "comment_count": 7,
    "latest_comment": [
      {
        "comment_id": 3088451,
        "uid": 100624499,
        "content": "买的………………唉………………",
        "createtime": 1507889871,
        "nickname": "Alucard52643",
        "avatar": "https://avatar.dmzj.com/70/be/70be91375d7de21e622b30f13aa4ffdc.png"
      },
      {
        "comment_id": 3087312,
        "uid": 104561734,
        "content": "我还是更喜欢原著……",
        "createtime": 1507871745,
        "nickname": "横竖茫茫一线天",
        "avatar": "https://avatar.dmzj.com/98/96/98963b24be63ec083c73d576594b502b.png"
      }
    ]
  }
}