{
  "id": 42423,
  "islong": 2,
  "direction": 1,
  "title": "弱势角色友崎君",
  "is_dmzj": 0,
  "cover": "https://images.dmzj.com/webpic/17/ruoshijuese.jpg",
  "description": "我们一起，来攻略这个人生游戏吧。",
  "last_updatetime": 1584623369,
  "last_update_chapter_name": "第16话",
  "copyright": 0,
  "first_letter": "r",
  "comic_py": "ruoshijiaoseyouqijun",
  "hidden": 1,
  "hot_num": 18645456,
  "hit_num": 6528216,
  "uid": null,
  "is_lock": 1,
  "last_update_chapter_id": 95129,
  "types": [
    {
      "tag_id": 13,
      "tag_name": "校园"
    },
    {
      "tag_id": 6316,
      "tag_name": "轻小说"
    }
  ],
  "status": [
    {
      "tag_id": 2309,
      "tag_name": "连载中"
    }
  ],
  "authors": [
    {
      "tag_id": 3787,
      "tag_name": "千田卫人"
    },
    {
      "tag_id": 14145,
      "tag_name": "屋久ユウキ"
    }
  ],
  "subscribe_num": 81344,
  "chapters": [],
  "comment": {
    "comment_count": 3842,
    "latest_comment": [
      {
        "comment_id": 30038182,
        "uid": 101370327,
        "content": "mk一下",
        "createtime": 1598759025,
        "nickname": "Alpha et Omega",
        "avatar": "https://avatar.dmzj.com/65/05/65056f62303c20b29a74895bdf56d697.png"
      },
      {
        "comment_id": 29967916,
        "uid": 106098095,
        "content": "之前缓存了任务还没开始下载  现在点继续下载居然还能下  嘿嘿嘿????",
        "createtime": 1598465854,
        "nickname": "dmzj_106098095",
        "avatar": "https://avatar.dmzj.com/26/23/26238637de437a9037c1c98ae0c0eeac.png"
      }
    ]
  },
  "is_need_login": 0
}