{
  "id": 51390,
  "islong": 2,
  "direction": 1,
  "title": "在异地海滨的邂逅",
  "is_dmzj": 0,
  "cover": "https://images.dmzj.com/webpic/6/zydhbdxg20191209.jpg",
  "description": "在异地海滨抱得小姐姐归。",
  "last_updatetime": 1575861380,
  "copyright": 0,
  "first_letter": "z",
  "hot_num": 1726442,
  "hit_num": 261357,
  "uid": null,
  "status": [
    {
      "tag_id": 2310,
      "tag_name": "已完结"
    }
  ],
  "types": [
    {
      "tag_id": 3243,
      "tag_name": "ゆり"
    }
  ],
  "authors": [
    {
      "tag_id": 15166,
      "tag_name": "泷岛朝香"
    }
  ],
  "subscribe_num": 8037,
  "chapters": [
    {
      "title": "连载",
      "data": [
        {
          "chapter_id": 95689,
          "chapter_title": "1话",
          "updatetime": 1575861380,
          "filesize": 3718752,
          "chapter_order": 10
        }
      ]
    }
  ],
  "comment": {
    "comment_count": 213,
    "latest_comment": [
      {
        "comment_id": 29177390,
        "uid": 29454749,
        "content": "好",
        "createtime": 1595525018,
        "nickname": "白井黑子爱炮姐",
        "avatar": "https://avatar.dmzj.com/37/18/371893554a581f4708c3d71fe8e5688b.png"
      },
      {
        "comment_id": 29063576,
        "uid": 111116694,
        "content": "后面说墨索里尼的hhhh",
        "createtime": 1595139311,
        "nickname": "dmzj_111116694",
        "avatar": "https://avatar.dmzj.com/63/44/634436106b0dc60d6ea6acad33bf7033.png"
      }
    ]
  }
}