{
  "id": 8810,
  "islong": 2,
  "direction": 1,
  "title": "爆杀梅兰克莉",
  "is_dmzj": 0,
  "cover": "https://images.dmzj.com/webpic/14/baosha.jpg",
  "description": "天野洋一新短篇，当男孩遇到女孩，故事就正式展开了。",
  "last_updatetime": 1337305958,
  "copyright": 0,
  "first_letter": "b",
  "hot_num": 44869,
  "hit_num": 511175,
  "uid": null,
  "types": [
    {
      "tag_id": 4,
      "tag_name": "冒险"
    }
  ],
  "authors": [
    {
      "tag_id": 918,
      "tag_name": "天野洋一"
    }
  ],
  "status": [
    {
      "tag_id": 2310,
      "tag_name": "已完结"
    }
  ],
  "subscribe_num": 212,
  "chapters": [
    {
      "title": "连载",
      "data": [
        {
          "chapter_id": 18768,
          "chapter_title": "1话",
          "updatetime": 1337305958,
          "filesize": 6231916,
          "chapter_order": 10
        }
      ]
    }
  ],
  "comment": {
    "comment_count": 7,
    "latest_comment": [
      {
        "comment_id": 3043094,
        "uid": 102178355,
        "content": "紫苑装啊",
        "createtime": 1507299609,
        "nickname": "黑色麋鹿",
        "avatar": "https://avatar.dmzj.com/82/50/8250a6cfc92fc1a1a0e5d5a549f18826.png"
      },
      {
        "comment_id": 157800,
        "uid": 13868479,
        "content": "庶民凡人男主這名子讓人無力吐嘈",
        "createtime": 1379438656,
        "nickname": "x632zero",
        "avatar": "https://avatar.dmzj.com/a6/83/a683a51dece160d7d294486344916cdd.png"
      }
    ]
  }
}