{
  "id": 39217,
  "islong": 2,
  "direction": 1,
  "title": "Sweet Session",
  "is_dmzj": 0,
  "cover": "https://images.dmzj.com/webpic/13/161117ss.jpg",
  "description": "(砲雷撃戦 -日出洋制圧戦-) [おたうT-R (皇ハマオ)] スイートセッション (艦隊これくしょん -艦これ-) [CE竹隐庭]",
  "last_updatetime": 1479436975,
  "last_update_chapter_name": "全一话",
  "copyright": 0,
  "first_letter": "s",
  "comic_py": "sweetsession",
  "hidden": 0,
  "hot_num": 62296,
  "hit_num": 122843,
  "uid": null,
  "is_lock": 0,
  "last_update_chapter_id": 60153,
  "types": [
    {
      "tag_id": 5,
      "tag_name": "欢乐向"
    },
    {
      "tag_id": 13627,
      "tag_name": "舰娘"
    }
  ],
  "status": [
    {
      "tag_id": 2310,
      "tag_name": "已完结"
    }
  ],
  "authors": [
    {
      "tag_id": 3391,
      "tag_name": "皇ハマオ"
    }
  ],
  "subscribe_num": 703,
  "chapters": [
    {
      "title": "连载",
      "data": [
        {
          "chapter_id": 60153,
          "chapter_title": "1话",
          "updatetime": 1479436975,
          "filesize": 2793158,
          "chapter_order": 10
        }
      ]
    }
  ],
  "comment": {
    "comment_count": 7,
    "latest_comment": [
      {
        "comment_id": 1480414,
        "uid": 101695210,
        "content": "响好萌啊",
        "createtime": 1479450808,
        "nickname": "零殇",
        "avatar": "https://avatar.dmzj.com/1f/bd/1fbde9e0a846aec13a5f7fee54223ae8.png"
      },
      {
        "comment_id": 1480046,
        "uid": 102328453,
        "content": "okaeri",
        "createtime": 1479443075,
        "nickname": "伊佐84349",
        "avatar": "https://avatar.dmzj.com/76/31/7631fadc63eea6b3f54deb5bf0ea60a3.png"
      }
    ]
  },
  "url_links": [],
  "isHideChapter": "0",
  "dh_url_links": [
    {
      "title": "网页端",
      "list": []
    },
    {
      "title": "APP端",
      "list": []
    }
  ],
  "is_dot": "0"
}