{
  "id": 41324,
  "islong": 2,
  "direction": 1,
  "title": "灵梦收集",
  "is_dmzj": 0,
  "cover": "https://images.dmzj.com/webpic/10/lingmengshoujifengmianl.jpg",
  "description": "各式各样的灵梦",
  "last_updatetime": 1503741951,
  "last_update_chapter_name": "全一话",
  "copyright": 0,
  "first_letter": "l",
  "comic_py": "lingmengshouji",
  "hidden": 0,
  "hot_num": 657353,
  "hit_num": 133701,
  "uid": null,
  "is_lock": 0,
  "last_update_chapter_id": 64506,
  "status": [
    {
      "tag_id": 2310,
      "tag_name": "已完结"
    }
  ],
  "types": [
    {
      "tag_id": 5077,
      "tag_name": "东方"
    }
  ],
  "authors": [
    {
      "tag_id": 13670,
      "tag_name": "萩原凛"
    }
  ],
  "subscribe_num": 3041,
  "chapters": [
    {
      "title": "连载",
      "data": [
        {
          "chapter_id": 64506,
          "chapter_title": "1话",
          "updatetime": 1503741951,
          "filesize": 1123876,
          "chapter_order": 10
        }
      ]
    }
  ],
  "comment": {
    "comment_count": 132,
    "latest_comment": [
      {
        "comment_id": 27057366,
        "uid": 104287759,
        "content": "留个标",
        "createtime": 1588473721,
        "nickname": "★ げんぱく☆",
        "avatar": "https://avatar.dmzj.com/28/39/2839f394c7e28edc8213befea662fbf3.png"
      },
      {
        "comment_id": 26739299,
        "uid": 101804576,
        "content": "要组个五色战队吗？",
        "createtime": 1587575214,
        "nickname": "里克66",
        "avatar": "https://avatar.dmzj.com/53/79/537901e45c9a04c0c272143894e43309.png"
      }
    ]
  },
  "url_links": [],
  "isHideChapter": "0",
  "dh_url_links": [
    {
      "title": "网页端",
      "list": []
    },
    {
      "title": "APP端",
      "list": []
    }
  ],
  "is_dot": "0"
}