{
  "id": 41780,
  "islong": 2,
  "direction": 2,
  "title": "虚拟临界",
  "is_dmzj": 0,
  "cover": "https://images.dmzj.com/img/webpic/10/1003080301507888091.jpg",
  "description": "苏维哲和夏辰逸因为为了抢一个新的游戏【Dream Fight Online】首发而结识成为好友。而擅长各种游戏的辰逸给游戏苦手的维哲提议说去维哲家一起破解游戏当中的操作难题。而在去维哲家一起玩游戏的时候，辰逸发现了维哲休学在家的妹妹慕涵，因为游戏玩的出众而使慕涵对于辰逸刮目相看并和自己的哥哥比较，而这时，辰逸便提议带上慕涵一起玩游戏，而成功安利慕涵也进入到了游戏当中。",
  "last_updatetime": 1508494780,
  "last_update_chapter_name": "第03话",
  "copyright": 1,
  "first_letter": "x",
  "comic_py": "xunilinjie",
  "hidden": 0,
  "hot_num": 84435,
  "hit_num": 1260189,
  "uid": 100308030,
  "is_lock": 0,
  "last_update_chapter_id": 70428,
  "types": [
    {
      "tag_id": 7,
      "tag_name": "科幻"
    },
    {
      "tag_id": 3245,
      "tag_name": "悬疑"
    }
  ],
  "status": [
    {
      "tag_id": 2309,
      "tag_name": "连载中"
    }
  ],
  "authors": [
    {
      "tag_id": 10236,
      "tag_name": "咪咕动漫有限公司"
    }
  ],
  "subscribe_num": 349,
  "chapters": [
    {
      "title": "连载",
      "data": [
        {
          "chapter_id": 70424,
          "chapter_title": "7话",
          "updatetime": 1508495286,
          "filesize": 1171829,
          "chapter_order": 7
        },
        {
          "chapter_id": 70425,
          "chapter_title": "6话",
          "updatetime": 1508495014,
          "filesize": 1316525,
          "chapter_order": 6
        },
        {
          "chapter_id": 70426,
          "chapter_title": "5话",
          "updatetime": 1508494977,
          "filesize": 1236851,
          "chapter_order": 5
        },
        {
          "chapter_id": 70427,
          "chapter_title": "4话",
          "updatetime": 1508494875,
          "filesize": 1258982,
          "chapter_order": 4
        },
        {
          "chapter_id": 70428,
          "chapter_title": "3话",
          "updatetime": 1508494780,
          "filesize": 1450428,
          "chapter_order": 3
        },
        {
          "chapter_id": 70131,
          "chapter_title": "2话",
          "updatetime": 1507888196,
          "filesize": 1249049,
          "chapter_order": 2
        },
        {
          "chapter_id": 70130,
          "chapter_title": "1话",
          "updatetime": 1507888167,
          "filesize": 2840511,
          "chapter_order": 1
        }
      ]
    }
  ],
  "author_notice": "",
  "comic_notice": "喜欢甜食和美漫，沉迷dc无法自拔，潜水模式多年，怕麻烦不喜欢怼人，通常是闭嘴画画模式",
  "comment": {
    "comment_count": 6,
    "latest_comment": [
      {
        "comment_id": 3329919,
        "uid": 100971713,
        "content": "月更么？",
        "createtime": 1511101804,
        "nickname": "故晴",
        "avatar": "https://avatar.dmzj.com/37/32/3732e72af180467556051b6455353196.png"
      },
      {
        "comment_id": 3139545,
        "uid": 104690480,
        "content": "fgo被盗版成了dgo？",
        "createtime": 1508576588,
        "nickname": "蜗牛灬",
        "avatar": "https://avatar.dmzj.com/de/a6/dea68bd0b680eb4185fe46395e3746f5.png"
      }
    ]
  },
  "url_links": [],
  "isHideChapter": "0",
  "dh_url_links": [
    {
      "title": "网页端",
      "list": []
    },
    {
      "title": "APP端",
      "list": []
    }
  ],
  "is_dot": "0"
}