{
  "id": 45271,
  "islong": 2,
  "direction": 1,
  "title": "水平线上的文月",
  "is_dmzj": 0,
  "cover": "https://images.dmzj.com/webpic/1/00shuopingnxianwenyue87.jpg",
  "description": "屹立在那水平线上的是……",
  "last_updatetime": 1574743870,
  "last_update_chapter_name": "第18话",
  "copyright": 0,
  "first_letter": "s",
  "comic_py": "shuipingxianshangdewenyue",
  "hidden": 0,
  "hot_num": 682450,
  "hit_num": 102087,
  "uid": null,
  "is_lock": 0,
  "last_update_chapter_id": 95208,
  "status": [
    {
      "tag_id": 2310,
      "tag_name": "已完结"
    }
  ],
  "authors": [
    {
      "tag_id": 13154,
      "tag_name": "ななてる"
    }
  ],
  "types": [
    {
      "tag_id": 13627,
      "tag_name": "舰娘"
    }
  ],
  "subscribe_num": 3299,
  "chapters": [
    {
      "title": "连载",
      "data": [
        {
          "chapter_id": 95208,
          "chapter_title": "18话",
          "updatetime": 1574743870,
          "filesize": 4064915,
          "chapter_order": 190
        },
        {
          "chapter_id": 94724,
          "chapter_title": "17话",
          "updatetime": 1573487179,
          "filesize": 1929838,
          "chapter_order": 180
        },
        {
          "chapter_id": 94047,
          "chapter_title": "16话",
          "updatetime": 1571652412,
          "filesize": 1683789,
          "chapter_order": 170
        },
        {
          "chapter_id": 94046,
          "chapter_title": "15话",
          "updatetime": 1571652227,
          "filesize": 2428336,
          "chapter_order": 160
        },
        {
          "chapter_id": 91807,
          "chapter_title": "14话",
          "updatetime": 1565932466,
          "filesize": 2048776,
          "chapter_order": 150
        },
        {
          "chapter_id": 89671,
          "chapter_title": "13话",
          "updatetime": 1561206565,
          "filesize": 1596099,
          "chapter_order": 140
        },
        {
          "chapter_id": 88470,
          "chapter_title": "12话",
          "updatetime": 1558025261,
          "filesize": 1550353,
          "chapter_order": 130
        },
        {
          "chapter_id": 88469,
          "chapter_title": "11话",
          "updatetime": 1558025219,
          "filesize": 1935131,
          "chapter_order": 120
        },
        {
          "chapter_id": 86398,
          "chapter_title": "10话",
          "updatetime": 1551670856,
          "filesize": 2088593,
          "chapter_order": 110
        },
        {
          "chapter_id": 85267,
          "chapter_title": "9话",
          "updatetime": 1548601436,
          "filesize": 1912839,
          "chapter_order": 100
        },
        {
          "chapter_id": 84261,
          "chapter_title": "8话",
          "updatetime": 1545543279,
          "filesize": 2968981,
          "chapter_order": 90
        },
        {
          "chapter_id": 83366,
          "chapter_title": "7话",
          "updatetime": 1543363300,
          "filesize": 1990158,
          "chapter_order": 80
        },
        {
          "chapter_id": 82676,
          "chapter_title": "6话",
          "updatetime": 1541522319,
          "filesize": 3122851,
          "chapter_order": 70
        },
        {
          "chapter_id": 81459,
          "chapter_title": "5话",
          "updatetime": 1538391255,
          "filesize": 3131831,
          "chapter_order": 60
        },
        {
          "chapter_id": 80387,
          "chapter_title": "4话",
          "updatetime": 1535817404,
          "filesize": 2521563,
          "chapter_order": 50
        },
        {
          "chapter_id": 79345,
          "chapter_title": "3话",
          "updatetime": 1533643461,
          "filesize": 3560691,
          "chapter_order": 40
        },
        {
          "chapter_id": 79344,
          "chapter_title": "2话",
          "updatetime": 1533643184,
          "filesize": 2812977,
          "chapter_order": 30
        },
        {
          "chapter_id": 79343,
          "chapter_title": "1话",
          "updatetime": 1533643129,
          "filesize": 2742379,
          "chapter_order": 20
        },
        {
          "chapter_id": 79342,
          "chapter_title": "0话",
          "updatetime": 1533643097,
          "filesize": 1125011,
          "chapter_order": 10
        }
      ]
    }
  ],
  "comment": {
    "comment_count": 91,
    "latest_comment": [
      {
        "comment_id": 22948353,
        "uid": 102419110,
        "content": "果然不愧是轮型阵 想赢全靠旗舰打出伤害",
        "createtime": 1577679113,
        "nickname": "暁の鳳",
        "avatar": "https://avatar.dmzj.com/a7/dd/a7ddf76fe468bd971c5948812ea23cef.png"
      },
      {
        "comment_id": 22559690,
        "uid": 106340367,
        "content": "小傻最后都出场了耶",
        "createtime": 1576037479,
        "nickname": "白露型の休比酱",
        "avatar": "https://avatar.dmzj.com/0c/ac/0cace367c1afbc82307425131f2f9d6c.png"
      }
    ]
  },
  "url_links": [],
  "isHideChapter": "0",
  "dh_url_links": [
    {
      "title": "网页端",
      "list": []
    },
    {
      "title": "APP端",
      "list": []
    }
  ],
  "is_dot": "0"
}