{
  "id": 51149,
  "islong": 2,
  "direction": 1,
  "title": "博丽神社的巫女妖梦",
  "is_dmzj": 0,
  "cover": "https://images.dmzj.com/webpic/17/191121blssdwnym.jpg",
  "description": "巫女服这个东西可真棒阿",
  "last_updatetime": 1574299347,
  "last_update_chapter_name": "短篇",
  "copyright": 0,
  "first_letter": "b",
  "comic_py": "bolishenshedewunvyaomeng",
  "hidden": 0,
  "hot_num": 51653,
  "hit_num": 11492,
  "uid": null,
  "is_lock": 0,
  "last_update_chapter_id": 91395,
  "status": [
    {
      "tag_id": 2310,
      "tag_name": "已完结"
    }
  ],
  "types": [
    {
      "tag_id": 5077,
      "tag_name": "东方"
    }
  ],
  "authors": [
    {
      "tag_id": 14378,
      "tag_name": "みりの"
    }
  ],
  "subscribe_num": 237,
  "chapters": [
    {
      "title": "连载",
      "data": [
        {
          "chapter_id": 91395,
          "chapter_title": "1话",
          "updatetime": 1574299347,
          "filesize": 4914503,
          "chapter_order": 10
        }
      ]
    }
  ],
  "comment": {
    "comment_count": 16,
    "latest_comment": [
      {
        "comment_id": 22345261,
        "uid": 109078101,
        "content": "所以麻薯才是本体喽",
        "createtime": 1574844838,
        "nickname": "一边睡觉一边睡觉",
        "avatar": "https://avatar.dmzj.com/97/d0/97d03d113d91857dc24c5d3b95c28bac.png"
      },
      {
        "comment_id": 22317941,
        "uid": 105675306,
        "content": "看看咋样吧",
        "createtime": 1574707617,
        "nickname": "南月樫雫",
        "avatar": "https://avatar.dmzj.com/52/48/5248523d6b0ca555c63bc36dc1e86979.png"
      }
    ]
  },
  "url_links": [],
  "isHideChapter": "0",
  "dh_url_links": [
    {
      "title": "网页端",
      "list": []
    },
    {
      "title": "APP端",
      "list": []
    }
  ],
  "is_dot": "0"
}