{
  "id": 6007,
  "islong": 2,
  "direction": 1,
  "title": "井之头高校Beasts",
  "is_dmzj": 0,
  "cover": "https://images.dmzj.com/webpic/9/jingzhixiaoyuan.jpg",
  "description": "井之头高校篮球队－一支拥有超美形球员的队伍,被却人称为「井之头高校Beasts」。没错！虽然队员个个拥有俊俏的外表,却也是擅於把妹的野兽。然而,当人气前锋升阳遇上冷冰冰球队经理真鱼时,一场硬碰硬的恋爱即将开始…",
  "last_updatetime": 1284022794,
  "last_update_chapter_name": "VOL01",
  "copyright": 0,
  "first_letter": "j",
  "comic_py": "jingzhitougaoxiaobeasts",
  "hidden": 0,
  "hot_num": 60639,
  "hit_num": 2471586,
  "uid": null,
  "is_lock": 0,
  "last_update_chapter_id": 12573,
  "types": [
    {
      "tag_id": 13,
      "tag_name": "校园"
    },
    {
      "tag_id": 3246,
      "tag_name": "纯爱"
    }
  ],
  "authors": [
    {
      "tag_id": 1412,
      "tag_name": "滨口奈津子"
    }
  ],
  "status": [
    {
      "tag_id": 2310,
      "tag_name": "已完结"
    }
  ],
  "subscribe_num": 315,
  "chapters": [
    {
      "title": "连载",
      "data": [
        {
          "chapter_id": 12573,
          "chapter_title": "1卷",
          "updatetime": 1284022794,
          "filesize": 10849697,
          "chapter_order": 10
        }
      ]
    }
  ],
  "comment": {
    "comment_count": 9,
    "latest_comment": [
      {
        "comment_id": 2128469,
        "uid": 104501014,
        "content": "这少女的吧",
        "createtime": 1493732706,
        "nickname": "想想现实",
        "avatar": "https://avatar.dmzj.com/5e/28/5e28781f5ea551093786faff64b33b27.png"
      },
      {
        "comment_id": 1749243,
        "uid": 101010549,
        "content": "就是，不是bl还放到bl里，怎么归类的",
        "createtime": 1486020465,
        "nickname": "Μόνος",
        "avatar": "https://avatar.dmzj.com/52/80/5280a4c0e2059d41e7fe0aaf209e4406.png"
      }
    ]
  },
  "url_links": [],
  "isHideChapter": "0",
  "dh_url_links": [
    {
      "title": "网页端",
      "list": []
    },
    {
      "title": "APP端",
      "list": []
    }
  ],
  "is_dot": "0"
}